Transcriber/__init__.py
Transcriber/config.py
Transcriber/py.typed
Transcriber/transcriber.py
Transcriber/export_handlers/__init__.py
Transcriber/export_handlers/exporter.py
Transcriber/logging/__init__.py
Transcriber/logging/config.py
Transcriber/logging/dummy_logfire.py
Transcriber/logging/logger.py
Transcriber/source_loaders/__init__.py
Transcriber/source_loaders/downloader.py
Transcriber/transcription_core/__init__.py
Transcriber/transcription_core/transcription_metadata.py
Transcriber/transcription_core/whisper_recognizer.py
Transcriber/types/__init__.py
Transcriber/types/export_type.py
Transcriber/types/segment_type.py
Transcriber/types/whisper/__init__.py
Transcriber/types/whisper/type_hints.py
Transcriber/utils/__init__.py
Transcriber/utils/file_utils.py
Transcriber/utils/progress.py
Transcriber/utils/time_utils.py
Transcriber/utils/whisper/__init__.py
Transcriber/utils/whisper/whisper_utils.py
transcriber-0.1.19.dist-info/METADATA
transcriber-0.1.19.dist-info/WHEEL
transcriber-0.1.19.dist-info/entry_points.txt
transcriber-0.1.19.dist-info/RECORD
