Metadata-Version: 2.4
Name: Transcriber
Version: 0.1.19
Summary: A simple tool to transcribe audio files
Author-email: NourEldin <noureldin.osama.saad@gmail.com>
Requires-Python: >=3.11
Requires-Dist: faster-whisper>=1.1.1
Requires-Dist: hf-xet>=1.1.0
Requires-Dist: humanize>=4.12.1
Requires-Dist: loguru>=0.7.3
Requires-Dist: openai-whisper>=20240930
Requires-Dist: pydantic-settings>=2.7.1
Requires-Dist: python-docx>=1.1.2
Requires-Dist: rich>=13.9.4
Requires-Dist: stable-ts>=2.18.3
Requires-Dist: yt-dlp>=2025.3.21
Provides-Extra: logfire
Requires-Dist: logfire>=3.8.1; extra == 'logfire'
